autobean_refactor/__init__.py
autobean_refactor/beancount.lark
autobean_refactor/editor.py
autobean_refactor/models/__init__.py
autobean_refactor/models/account.py
autobean_refactor/models/amount.py
autobean_refactor/models/balance.py
autobean_refactor/models/base.py
autobean_refactor/models/block_comment.py
autobean_refactor/models/bool.py
autobean_refactor/models/close.py
autobean_refactor/models/commodity.py
autobean_refactor/models/compound_amount.py
autobean_refactor/models/cost.py
autobean_refactor/models/cost_component.py
autobean_refactor/models/cost_spec.py
autobean_refactor/models/currency.py
autobean_refactor/models/custom.py
autobean_refactor/models/date.py
autobean_refactor/models/document.py
autobean_refactor/models/escaped_string.py
autobean_refactor/models/event.py
autobean_refactor/models/file.py
autobean_refactor/models/generated/__init__.py
autobean_refactor/models/generated/amount.py
autobean_refactor/models/generated/balance.py
autobean_refactor/models/generated/close.py
autobean_refactor/models/generated/commodity.py
autobean_refactor/models/generated/compound_amount.py
autobean_refactor/models/generated/cost_spec.py
autobean_refactor/models/generated/custom.py
autobean_refactor/models/generated/document.py
autobean_refactor/models/generated/event.py
autobean_refactor/models/generated/file.py
autobean_refactor/models/generated/ignored_line.py
autobean_refactor/models/generated/include.py
autobean_refactor/models/generated/meta_item.py
autobean_refactor/models/generated/note.py
autobean_refactor/models/generated/number_expr.py
autobean_refactor/models/generated/number_paren_expr.py
autobean_refactor/models/generated/number_unary_expr.py
autobean_refactor/models/generated/open.py
autobean_refactor/models/generated/option.py
autobean_refactor/models/generated/pad.py
autobean_refactor/models/generated/plugin.py
autobean_refactor/models/generated/popmeta.py
autobean_refactor/models/generated/poptag.py
autobean_refactor/models/generated/posting.py
autobean_refactor-0.2.6.dist-info/WHEEL
autobean_refactor-0.2.6.dist-info/METADATA
autobean_refactor-0.2.6.dist-info/licenses/LICENSE
autobean_refactor-0.2.6.dist-info/RECORD
