Metadata-Version: 2.1
Name: autobean-refactor
Version: 0.2.6
Summary: An ergonomic and losess beancount manipulation library
License: MIT
Author-email: SEIAROTg <seiarotg@gmail.com>
Requires-Python: >=3.10
Requires-Dist: lark>=1.1.5
Requires-Dist: typing-extensions>=4.4.0
